[
  {
    "name": "Armaretto Sour",
    "style": "Sour",
    "base": "Other",
    "category": "Classics",
    "ingredients": [
      { "amount": 45,   "unit": "mL", "ingredient": "amaretto" },
      { "amount": 22.5, "unit": "mL", "ingredient": "bourbon" },
      { "amount": 22.5, "unit": "mL", "ingredient": "lemon juice" },
      { "amount": 5,    "unit": "mL", "ingredient": "simple syrup" },
      "egg white"
    ],
    "method": ["shake", "double strain"],
    "notes": "Morgenthaler's amaretto sour"
  },
  {
    "name": "Brandy Alexander",
    "style": "Alexander",
    "base": "Brandy",
    "category": "Classics",
    "img": "images/alexander.jpg",
    "ingredients": [
      { "amount": 25,   "unit": "mL", "ingredient": "brandy" },
      { "amount": 25,   "unit": "mL", "ingredient": "creme de cacao" },
      { "amount": 30,   "unit": "mL", "ingredient": "cream" }
    ],
    "method": ["shake", "double strain"]
  },
  {
    "name": "Chrysanthemum",
    "style": "Martini",
    "base": "Other",
    "category": "Classics",
    "img": "images/chrysanthemum.jpg",
    "ingredients": [
      { "amount": 50,   "unit": "mL", "ingredient": "dry vermouth" },
      { "amount": 15,   "unit": "mL", "type": "DOM Benedictine", "ingredient": "" },
      { "amount": 2.5,  "unit": "mL", "ingredient": "absinthe" }
    ],
    "method": ["stir", "express orange🍊 peel"]
  },
  {
    "name": "Manhattan",
    "style": "Martini",
    "base": "Whisky",
    "category": "Classics",
    "img": "images/manhattan.jpg",
    "ingredients": [
      { "amount": 50,   "unit": "mL", "type": "rye", "ingredient": "whisky" },
      { "amount": 25,   "unit": "mL", "type": "Antica Formula","ingredient": "sweet vermouth" },
      { "amount": 1,    "unit": "dash", "type": "Angostura", "ingredient": "bitters" }
    ],
    "method": ["stir", "express orange🍊 peel"]
  },
  {
    "name": "Margarita",
    "style": "Sidecar",
    "base": "Tequila",
    "category": "Classics",
    "img": "images/margarita.jpg",
    "ingredients": [
      { "amount": 45,   "unit": "mL", "ingredient": "tequila" },
      { "amount": 22.5, "unit": "mL", "type": "Cointreau", "ingredient": "triple sec" },
      { "amount": 22.5, "unit": "mL", "ingredient": "lime juice" }
    ],
    "method": [
      "shake",
      "thin salt rim"
    ]
  },
  {
    "name": "Margarita (preferred)",
    "style": "Sour",
    "base": "Tequila",
    "category": "Classics",
    "img": "images/margarita.jpg",
    "ingredients": [
      { "amount": 50,   "unit": "mL", "ingredient": "tequila" },
      { "amount": 10,   "unit": "mL", "ingredient": "agave nectar" },
      { "amount": 25,   "unit": "mL", "ingredient": "lime juice" },
      "orange peel"
    ],
    "method": [
      "regal shake with orange peel",
      "thin salt rim",
      "express orange🍊 peel",
      "(if using Monin Agave Syrup, use about 15mL)"
    ]
  },
  {
    "name": "Sidecar",
    "style": "Sidecar",
    "base": "Brandy",
    "category": "Classics",
    "img": "images/sidecar.jpg",
    "ingredients": [
      { "amount": 45,   "unit": "mL", "ingredient": "brandy" },
      { "amount": 22.5, "unit": "mL", "type": "Cointreau", "ingredient": "triple sec" },
      { "amount": 22.5, "unit": "mL", "ingredient": "lemon juice" },
      { "amount": 5 ,   "unit": "mL", "ingredient": "simple syrup" }
    ],
    "method": [
      "shake with slice of orange🍊",
      "express orange🍊 peel",
      "(if using sugar rim, don't add sugar syrup)"
    ]
  },
  {
    "name": "Whisky Highball",
    "style": "Highball",
    "base": "Whisky",
    "category": "Classics",
    "img": "images/whisky_highball.jpg",
    "ingredients": [
      { "amount": 45,   "unit": "mL", "ingredient": "whisky" },
      { "amount": 90,   "unit": "mL", "ingredient": "soda water" }
    ],
    "method": [
      "add whisky and half ice, stir",
      "add the rest of the ice",
      "add soda",
      "using barspoon, smoothly lift ice up from bottom a few times to mix",
      "(optional) express lemon🍋 zest"
    ]
  }
]
